SumitGAY/GAY.py
SumitGAY/__init__.py
SumitGAY/main.py
naman_step_sis-0.1.0.dist-info/METADATA
naman_step_sis-0.1.0.dist-info/WHEEL
naman_step_sis-0.1.0.dist-info/top_level.txt
naman_step_sis-0.1.0.dist-info/RECORD
