Metadata-Version: 2.4
Name: naman_step_sis
Version: 0.1.0
Summary: World's most sus typing effect meme package
Author: Shreyansh
Author-email: SumitLigmaBalls6911@gmail.com
Classifier: Programming Language :: Python :: 3
Classifier: Topic :: Utilities
Classifier: Development Status :: 3 - Alpha
Requires-Python: >=3.7
Dynamic: author
Dynamic: author-email
Dynamic: classifier
Dynamic: description
Dynamic: description-content-type
Dynamic: requires-python
Dynamic: summary
